setup.py
Lango.egg-info/PKG-INFO
Lango.egg-info/SOURCES.txt
Lango.egg-info/dependency_links.txt
Lango.egg-info/requires.txt
Lango.egg-info/top_level.txt
lango/__init__.py
lango/matcher.py
lango/parser.py