Metadata-Version: 1.0
Name: Lango
Version: 0.20.0
Summary: Natural Language Framework for Matching Parse Trees and Modeling Conversation
Home-page: https://github.com/ayoungprogrammer/lango
Author: Michael Young
Author-email: michaelyoung1995@gmail.com
License: UNKNOWN
Platform: UNKNOWN
